main.py
cli/__init__.py
cli/dispatcher.py
cli/shell.py
cli/utils.py
cli/modules/__init__.py
cli/modules/config.py
cli/modules/register.py
cli/modules/show.py
cli/modules/system.py
cli/modules/twamp.py
cli/modules/xdp_mef_switch.py
plugins/__init__.py
plugins/twamp/onyx.py
plugins/twamp/readme.md
plugins/twamp/__pycache__/onyx.cpython-38.pyc
plugins/twamp/__pycache__/onyx.cpython-39.pyc
plugins/xdp_mef_switch/Makefile
plugins/xdp_mef_switch/README.md
plugins/xdp_mef_switch/__init__.py
plugins/xdp_mef_switch/forwarding_maps.bpf.h
plugins/xdp_mef_switch/forwarding_table.py
plugins/xdp_mef_switch/map_utils.py
plugins/xdp_mef_switch/utils.py
plugins/xdp_mef_switch/xdp_forwarding.c
plugins/xdp_mef_switch/xdp_forwarding.o
plugins/xdp_mef_switch/xdp_loader.py
plugins/xdp_mef_switch/__pycache__/__init__.cpython-39.pyc
plugins/xdp_mef_switch/__pycache__/forwarding_plugin.cpython-39.pyc
plugins/xdp_mef_switch/__pycache__/forwarding_table.cpython-39.pyc
plugins/xdp_mef_switch/__pycache__/map_utils.cpython-39.pyc
plugins/xdp_mef_switch/__pycache__/utils.cpython-39.pyc
plugins/xdp_mef_switch/__pycache__/xdp_loader.cpython-39.pyc
vmark_node-0.3.9.dist-info/licenses/LICENSE
vmark_node-0.3.9.dist-info/METADATA
vmark_node-0.3.9.dist-info/WHEEL
vmark_node-0.3.9.dist-info/entry_points.txt
vmark_node-0.3.9.dist-info/top_level.txt
vmark_node-0.3.9.dist-info/RECORD
