Metadata-Version: 2.4
Name: vmark-node
Version: 0.3.9
Summary: An Ethernet software-based open source demarcation NID
Home-page: https://github.com/xmas-ar/vMark-node
Author: Pathgate
License: GPL-3.0-only
Classifier: Programming Language :: Python :: 3.9
Classifier: Programming Language :: Python :: 3.10
Classifier: License :: OSI Approved :: GNU General Public License v3 (GPLv3)
Classifier: Operating System :: OS Independent
Requires-Python: >=3.9
License-File: LICENSE
Requires-Dist: prompt_toolkit<4.0.0,>=3.0.0
Requires-Dist: pyroute2<0.7.0,>=0.6.9
Requires-Dist: ethtool==0.15
Requires-Dist: numba>=0.55.0
Requires-Dist: pytest>=6.0
Dynamic: author
Dynamic: classifier
Dynamic: description
Dynamic: description-content-type
Dynamic: home-page
Dynamic: license
Dynamic: license-file
Dynamic: requires-dist
Dynamic: requires-python
Dynamic: summary
